{
  "version": 1,
  "bugs": [
    {
      "id": "bug-001",
      "timestamp": "2026-04-09T21:38:34.510Z",
      "error_message": "Significant refactor of ",
      "file": "src/utils.rs",
      "root_cause": "11 lines replaced/restructured",
      "fix": "Rewrote 96→32 lines (11 removed)",
      "tags": [
        "auto-detected",
        "refactor",
        "rs"
      ],
      "related_bugs": [],
      "occurrences": 1,
      "last_seen": "2026-04-09T21:38:34.510Z"
    },
    {
      "id": "bug-002",
      "timestamp": "2026-04-09T21:46:19.219Z",
      "error_message": "CSS fix: margin-top, margin-bottom",
      "file": "static/style.css",
      "root_cause": "margin-top: 10px → 0; margin-bottom: 0px → 1.25rem",
      "fix": "Changed margin-top: 10px → 0; margin-bottom: 0px → 1.25rem",
      "tags": [
        "auto-detected",
        "style-fix",
        "css"
      ],
      "related_bugs": [],
      "occurrences": 2,
      "last_seen": "2026-04-09T21:46:27.383Z"
    },
    {
      "id": "bug-003",
      "timestamp": "2026-04-09T21:46:29.889Z",
      "error_message": "Wrong reference: controls should be playsinline",
      "file": "templates/utils.html",
      "root_cause": "Used \"controls\" instead of \"playsinline\"",
      "fix": "Changed controls → playsinline",
      "tags": [
        "auto-detected",
        "wrong-reference",
        "html"
      ],
      "related_bugs": [],
      "occurrences": 1,
      "last_seen": "2026-04-09T21:46:29.889Z"
    },
    {
      "id": "bug-004",
      "timestamp": "2026-04-09T21:46:35.251Z",
      "error_message": "Incorrect value in code",
      "file": "templates/utils.html",
      "root_cause": "Had \"Gallery image\"",
      "fix": "Changed to \"async\"",
      "tags": [
        "auto-detected",
        "wrong-value",
        "html"
      ],
      "related_bugs": [],
      "occurrences": 4,
      "last_seen": "2026-04-09T21:47:23.778Z"
    },
    {
      "id": "bug-005",
      "timestamp": "2026-04-09T21:47:10.326Z",
      "error_message": "Incorrect value in code",
      "file": "templates/base.html",
      "root_cause": "Had \"stylesheet\"",
      "fix": "Changed to \"preload\"",
      "tags": [
        "auto-detected",
        "wrong-value",
        "html"
      ],
      "related_bugs": [],
      "occurrences": 1,
      "last_seen": "2026-04-09T21:47:10.326Z"
    },
    {
      "id": "bug-006",
      "timestamp": "2026-04-10T15:03:21.633Z",
      "error_message": "Wrong reference: fca4d64 should be 532a452",
      "file": "../talos-argocd-proxmox/my-apps/media/redlib/deployment.yaml",
      "root_cause": "Used \"fca4d64\" instead of \"532a452\"",
      "fix": "Changed fca4d64 → 532a452",
      "tags": [
        "auto-detected",
        "wrong-reference",
        "yaml"
      ],
      "related_bugs": [],
      "occurrences": 1,
      "last_seen": "2026-04-10T15:03:21.633Z"
    },
    {
      "id": "bug-007",
      "timestamp": "2026-04-10T21:20:23.674Z",
      "error_message": "Incorrect value in code",
      "file": "Cargo.toml",
      "root_cause": "Had \"1.83\"",
      "fix": "Changed to \"1.86\"",
      "tags": [
        "auto-detected",
        "wrong-value",
        "toml"
      ],
      "related_bugs": [],
      "occurrences": 1,
      "last_seen": "2026-04-10T21:20:23.674Z"
    },
    {
      "id": "bug-008",
      "timestamp": "2026-04-12T00:00:00.000Z",
      "error_message": "CI Pull Request workflow failing: client::test_banned_sub, test_gated_sub, test_default_subscriptions, test_localization_popular all FAILED",
      "file": "src/client.rs",
      "root_cause": "All client tests make live HTTP requests to Reddit, which blocks GitHub Actions IPs. Also pull-request.yml was missing cmake/clang build deps for BoringSSL compilation.",
      "fix": "Added #[ignore] to all 7 network-dependent tests in client.rs. Added cmake/perl/pkg-config/libclang-dev to test and clippy jobs in pull-request.yml.",
      "tags": [
        "ci",
        "github-actions",
        "tests",
        "network",
        "boringssl",
        "reddit-blocking"
      ],
      "related_bugs": [],
      "occurrences": 1,
      "last_seen": "2026-04-12T00:00:00.000Z"
    },
    {
      "id": "bug-009",
      "timestamp": "2026-04-13T03:55:45.204Z",
      "error_message": "Significant refactor of ",
      "file": ".github/workflows/main-rust.yml",
      "root_cause": "2 lines replaced/restructured",
      "fix": "Rewrote 9→12 lines (2 removed)",
      "tags": [
        "auto-detected",
        "refactor",
        "yml"
      ],
      "related_bugs": [],
      "occurrences": 1,
      "last_seen": "2026-04-13T03:55:45.204Z"
    },
    {
      "id": "bug-010",
      "timestamp": "2026-04-13T03:55:53.848Z",
      "error_message": "Significant refactor of ",
      "file": ".github/workflows/build-artifacts.yaml",
      "root_cause": "5 lines replaced/restructured",
      "fix": "Rewrote 14→18 lines (5 removed)",
      "tags": [
        "auto-detected",
        "refactor",
        "yaml"
      ],
      "related_bugs": [],
      "occurrences": 1,
      "last_seen": "2026-04-13T03:55:53.848Z"
    },
    {
      "id": "bug-011",
      "timestamp": "2026-04-15T11:51:38+03:00",
      "error_message": "Comment thread guide lines do not collapse or expand the thread when clicked",
      "file": "src/main.rs",
      "root_cause": "The browser could not load `/comment_threads.js` because Redlib serves static assets through explicit routes in `src/main.rs`, and the new file had no registered route. The JS was therefore never executed.",
      "fix": "Added an explicit `/comment_threads.js` route in `src/main.rs`, kept the guide line as a button, and bound each line directly to its sibling details element while syncing aria-expanded with the native collapse state.",
      "tags": [
        "comments",
        "ui",
        "interaction",
        "template",
        "javascript"
      ],
      "related_bugs": [],
      "occurrences": 3,
      "last_seen": "2026-04-15T12:03:18+03:00"
    },
    {
      "id": "bug-013",
      "timestamp": "2026-04-15T12:49:41+03:00",
      "error_message": "Collapsed comment gutters are inconsistent: some collapsed comments lose the visible line stub, and comment scores do not toggle the thread",
      "file": "templates/comment.html",
      "root_cause": "Only the guide line was wired as a toggle, and the gutter layout relied on a flexible `height: 100%` line that could collapse inconsistently when the comment body was hidden.",
      "fix": "Converted the score pill into the same toggle control, synced both controls through comment_threads.js, and changed the gutter CSS to keep a minimum visible line stub for collapsed comments.",
      "tags": [
        "comments",
        "ui",
        "interaction",
        "css",
        "javascript"
      ],
      "related_bugs": [
        "bug-011"
      ],
      "occurrences": 1,
      "last_seen": "2026-04-15T12:49:41+03:00"
    },
    {
      "id": "bug-012",
      "timestamp": "2026-04-15T12:01:54+03:00",
      "error_message": "Duplicate post cards render `post_footer` beside the title area instead of as a bottom footer row, making the layout look wrong",
      "file": "templates/duplicates.html",
      "root_cause": "Duplicate cards omitted the standard `.post_content` wrapper used by listing posts, and rendered `post_score` outside `post_footer`, so the footer markup did not align with the shared card layout.",
      "fix": "Wrapped duplicate card content in `.post_content` and moved the score into `.post_footer` alongside the comments link.",
      "tags": [
        "duplicates",
        "ui",
        "layout",
        "template",
        "footer"
      ],
      "related_bugs": [],
      "occurrences": 1,
      "last_seen": "2026-04-15T12:01:54+03:00"
    },
    {
      "id": "bug-013",
      "timestamp": "2026-04-15T12:04:20+03:00",
      "error_message": "Duplicate post score placement should align with the title row while keeping the footer reserved for comments",
      "file": "templates/duplicates.html",
      "root_cause": "Putting the score in the footer fixed the footer position but did not match the intended visual hierarchy for duplicate cards.",
      "fix": "Introduced a `post_title_row` wrapper, moved the score beside the title, and left only the comments link in the footer. Added minimal CSS to align the row cleanly.",
      "tags": [
        "duplicates",
        "ui",
        "layout",
        "template",
        "css"
      ],
      "related_bugs": [
        "bug-012"
      ],
      "occurrences": 1,
      "last_seen": "2026-04-15T12:04:20+03:00"
    },
    {
      "id": "bug-014",
      "timestamp": "2026-04-15T12:24:04+03:00",
      "error_message": "Subreddit feed cards look broken on mobile because the thumbnail stays beside the text/footer, and the score should sit next to the post title instead of in the footer",
      "file": "templates/utils.html",
      "root_cause": "List post cards kept a horizontal thumbnail layout at mobile widths, which squeezed footer items into awkward wraps, and the score remained in the footer instead of the title row.",
      "fix": "Moved the score into a shared `post_title_row` in the list post template and changed mobile feed cards to stack vertically with the thumbnail below the text content.",
      "tags": [
        "feed",
        "mobile",
        "ui",
        "layout",
        "template",
        "css"
      ],
      "related_bugs": [
        "bug-013"
      ],
      "occurrences": 1,
      "last_seen": "2026-04-15T12:24:04+03:00"
    },
    {
      "id": "bug-015",
      "timestamp": "2026-04-15T12:26:03+03:00",
      "error_message": "Mobile feed thumbnails should be full width, and posts without thumbnails should not render placeholder image boxes",
      "file": "templates/utils.html",
      "root_cause": "The list template always rendered a thumbnail container, including placeholder SVGs for self posts and posts without thumbnails, which looked especially broken after switching the mobile layout to bottom-stacked media.",
      "fix": "Rendered `.post_thumbnail` only when `post.thumbnail.url` exists and updated mobile thumbnail CSS to use full-width blocks with auto height.",
      "tags": [
        "feed",
        "mobile",
        "thumbnail",
        "ui",
        "template",
        "css"
      ],
      "related_bugs": [
        "bug-014"
      ],
      "occurrences": 1,
      "last_seen": "2026-04-15T12:26:03+03:00"
    },
    {
      "id": "bug-016",
      "timestamp": "2026-04-15T12:30:00+03:00",
      "error_message": "There is no up/down arrow next to the score on desktop",
      "file": "static/style.css",
      "root_cause": "The `post_score::before` arrow was defined only inside the `@media screen and (max-width: 507px)` block, so desktop layouts never rendered it.",
      "fix": "Moved the `post_score::before` arrow into the base `.post_score` styles and added inline-flex alignment so the arrow and number line up consistently on all screen sizes.",
      "tags": [
        "score",
        "desktop",
        "ui",
        "css"
      ],
      "related_bugs": [
        "bug-014",
        "bug-015"
      ],
      "occurrences": 1,
      "last_seen": "2026-04-15T12:30:00+03:00"
    },
    {
      "id": "bug-017",
      "timestamp": "2026-04-15T12:30:58+03:00",
      "error_message": "The post title is full width on desktop and clicking outside the title still opens the post",
      "file": "templates/utils.html",
      "root_cause": "The `.post_title` anchor was the flex item with `flex: 1`, so it expanded across the remaining horizontal space in the title row.",
      "fix": "Wrapped the title link in a `.post_title_wrap` container that owns the flexible width, leaving the anchor sized to its text content.",
      "tags": [
        "feed",
        "desktop",
        "click-target",
        "ui",
        "template",
        "css"
      ],
      "related_bugs": [
        "bug-014",
        "bug-016"
      ],
      "occurrences": 1,
      "last_seen": "2026-04-15T12:30:58+03:00"
    },
    {
      "id": "bug-018",
      "timestamp": "2026-04-15T12:43:38+03:00",
      "error_message": "Only on Firefox some scores look weirdly cut on a new line",
      "file": "static/style.css",
      "root_cause": "Firefox was allowed to wrap the inline score content, so the vote arrow and digits could break onto separate lines in narrow title rows.",
      "fix": "Added `white-space: nowrap` to `.post_score` so the arrow and score stay together across browsers.",
      "tags": [
        "firefox",
        "score",
        "ui",
        "css"
      ],
      "related_bugs": [
        "bug-016"
      ],
      "occurrences": 1,
      "last_seen": "2026-04-15T12:43:38+03:00"
    }
  ]
}
